{
  "id": "in-the-workplace",
  "order": 7,
  "unit": "Unit 2 — Competition",
  "title": "2C In the Workplace — Как сравнивать и оценивать идеи",
  "contentMd": "## 2C In the Workplace — Как сравнивать и оценивать идеи\n\n### Простая суть\n\nКогда нужно сравнить две вещи или оценить, насколько что-то полезно, английский предлагает целую шкалу — от «разница колоссальная» до «разницы нет вообще». Хочешь сказать, что один вариант **намного** лучше? Используй **way / miles / loads / far / considerably**. Разница почти незаметна? Бери **a little / slightly / marginally**. А если вообще никакой — **just as … as / every bit as … as**.\n\nДля оценки эффективности — своя палитра: от **invaluable** (бесценный) до **a waste of time** (пустая трата времени).\n\n### Как это работает\n\n**Сравнение (Comparison)**\n\n| Разница | Неформально | Нейтрально | Формально |\n|---|---|---|---|\n| **Большая** | **way / miles / loads** more … than | **much / a lot / far** more … than | **considerably / significantly / infinitely** more … than |\n| **Большая** (отрицание) | — | **nowhere near** as … as | — |\n| **Малая** | — | **a little / slightly / a bit** more … than / **almost** as … as | **marginally** more … than |\n| **Нет разницы** | — | **just as … as** / **every bit as … as** / **equally … as** | — |\n\n**Оценка (Evaluation)**\n\n| Эффект | Фразы |\n|---|---|\n| ✅ **Эффективно** | **be valuable / invaluable / effective / useful** for (someone); **be effective / useful in (doing sth)** |\n| ❌ **Неэффективно** | **be useless** for (someone) / **at (doing sth)**; **be a waste of time / energy**; **be ineffective / unhelpful** for (someone) |\n\n### Живые примеры\n\n- It's **much easier** to give a bonus than create a whole new pay system. *(**Гораздо проще** выдать премию, чем создавать новую систему оплаты.)*\n- A four-day week is **infinitely better** than a five-day week. *(Четырёхдневка **бесконечно лучше** пятидневки.)*\n- My salary is **marginally lower** than yours. *(Моя зарплата **незначительно ниже** твоей.)*\n- This computer is **every bit as useless** as the last one! *(Этот комп **ничуть не лучше** прошлого!)*\n- The mentor programme is **invaluable** for people who need support. *(Программа наставничества **бесценна** для тех, кому нужна поддержка.)*\n- It's **a waste of time and effort** for the company. *(Это **пустая трата времени и сил** для компании.)*\n\n### Лайфхак для запоминания\n\nПредставь шкалу от 0 до 10:\n- **0** (нет разницы) → *just as … as, every bit as … as*\n- **1–3** (чуть-чуть) → *slightly, a bit, marginally*\n- **7–9** (заметно) → *much, far, a lot*\n- **10** (огромная) → *way, miles, loads, infinitely*\n- **Отрицание** → *nowhere near as … as* («даже рядом не стоит»)\n\nДля оценки: **in** + герундий (*effective in helping*), **for** + человек (*useful for junior staff*). Запомни как пару: *in — процесс, for — человек*.",
  "examples": [
    "It's much easier to give a bonus than create a whole new pay system.",
    "A four-day week is infinitely better than a five-day week.",
    "My salary is marginally lower than yours.",
    "This computer is every bit as useless as the last one!",
    "The mentor programme is invaluable for people who need support."
  ]
}
