{
  "lessonId": "role-models",
  "title": "3D Role Models — Описание вдохновляющих людей",
  "items": [
    {
      "term": "role model",
      "translation": "образец для подражания",
      "example": "My grandmother has always been my role model."
    },
    {
      "term": "inspiration",
      "translation": "вдохновение",
      "example": "She is an inspiration to young people everywhere."
    },
    {
      "term": "admire",
      "translation": "восхищаться",
      "example": "I admire people who work hard to achieve their dreams."
    },
    {
      "term": "look up to",
      "translation": "уважать, равняться на",
      "example": "Many young athletes look up to professional players."
    },
    {
      "term": "achieve",
      "translation": "достигать",
      "example": "It took years of hard work to achieve her goals."
    },
    {
      "term": "path",
      "translation": "путь",
      "example": "Everyone has to find their own path in life."
    },
    {
      "term": "goal",
      "translation": "цель",
      "example": "Setting clear goals is the first step to success."
    },
    {
      "term": "motivate",
      "translation": "мотивировать",
      "example": "A good teacher knows how to motivate their students."
    },
    {
      "term": "passionate",
      "translation": "страстно увлечённый",
      "example": "She is passionate about helping underprivileged children."
    },
    {
      "term": "visionary",
      "translation": "провидец, дальновидный человек",
      "example": "Steve Jobs was a visionary who changed the way we use technology."
    }
  ]
}
