{
  "id": "6B-quiet",
  "order": 22,
  "unit": "Unit 6 — Psychology",
  "title": "Quiet",
  "contentMd": "## Reported orders, requests and advice\n\n### Простая суть\n\nПередаём чужие слова без кавычек: приказ, просьба, совет. Глагол + **to infinitive** (или **not to**). Глагол выбираем по смыслу: *tell* — приказ, *ask* — просьба, *advise* — совет.\n\n### Как это работает\n\n- Order: **told + sb + to do / not to do**\n- Request: **asked + sb + to do**\n- Advice: **advised + sb + to do** | **suggested + -ing**\n- Также: **warned, reminded, encouraged**\n\n### Живые примеры\n\n- She **advised me not to** overwork. — Она посоветовала мне не перерабатывать.\n- He **asked everyone to keep** quiet during the recording. — Он попросил всех молчать во время записи.\n- The manager **told him to close** the door. — Менеджер сказал ему закрыть дверь.\n- She **suggested taking** a break instead of pushing through. — Она предложила сделать перерыв вместо того чтобы давить на себя.\n\n### Лайфхак для запоминания\n\nПрямая речь → убери кавычки, сдвинь время, **to infinitive**. *Suggest* часто с **-ing** или **that + subjunctive**.",
  "examples": [
    "She **advised me not to** overwork.",
    "He **asked everyone to keep** quiet during the recording.",
    "The manager **told him to close** the door.",
    "She **suggested taking** a break instead of pushing through."
  ]
}
